deepadapter/__init__.py
deepadapter/models/__init__.py
deepadapter/models/data_loader.py
deepadapter/models/dl_utils.py
deepadapter/models/trainer.py
deepadapter/params/__init__.py
deepadapter/params/dl_finetune_params.py
deepadapter/params/dl_params.py
deepadapter/params/dl_params_purity.py
deepadapter/run/__init__.py
deepadapter/run/run.py
deepadapter/utils/__init__.py
deepadapter/utils/data_utils.py
deepadapter/utils/decomposition_utils.py
deepadapter/utils/finetune_utils.py
deepadapter/utils/triplet.py
deepadapter/utils/utils.py
deepadapter-1.1.0.dist-info/LICENSE
deepadapter-1.1.0.dist-info/METADATA
deepadapter-1.1.0.dist-info/WHEEL
deepadapter-1.1.0.dist-info/top_level.txt
deepadapter-1.1.0.dist-info/RECORD
