Metadata-Version: 2.1
Name: deepadapter
Version: 1.1.0
Summary: # DeepAdapter
Author: MJ Zhang
Author-email: mengji.zhang@gmail.com
License: BSD-3
Platform: UNKNOWN
Classifier: Programming Language :: Python :: 3
Classifier: Operating System :: OS Independent
Requires-Python: >=3.9
License-File: LICENSE
Requires-Dist: notebook
Requires-Dist: matplotlib
Requires-Dist: numpy (<2)
Requires-Dist: openpyxl
Requires-Dist: pandas
Requires-Dist: scikit-learn
Requires-Dist: scipy
Requires-Dist: tqdm
Requires-Dist: umap-learn
Requires-Dist: torch
